{"name":"build-javascript","namedChunkGroups":{"polyfill":{"name":"polyfill","assets":[{"name":"webpack-runtime-f7abd37263ef5f9b6cab.js","size":3234},{"name":"polyfill-5e40f9ff782d94fbed19.js","size":85874}],"filteredAssets":0,"assetsSize":89108,"filteredAuxiliaryAssets":2,"auxiliaryAssetsSize":221400},"app":{"name":"app","assets":[{"name":"webpack-runtime-f7abd37263ef5f9b6cab.js","size":3234},{"name":"framework-587f98a0a1a6eaf716e3.js","size":140759},{"name":"app-e33d6fbe3bb332ff4936.js","size":108362}],"filteredAssets":0,"assetsSize":252355,"filteredAuxiliaryAssets":3,"auxiliaryAssetsSize":755158},"component---src-pages-404-tsx":{"name":"component---src-pages-404-tsx","assets":[{"name":"component---src-pages-404-tsx-616da19c675861e2db87.js","size":841}],"filteredAssets":0,"assetsSize":841,"filteredAuxiliaryAssets":1,"auxiliaryAssetsSize":1869},"component---src-pages-index-tsx":{"name":"component---src-pages-index-tsx","assets":[{"name":"component---src-pages-index-tsx-233fda072165a386d4f8.js","size":4765}],"filteredAssets":0,"assetsSize":4765,"filteredAuxiliaryAssets":1,"auxiliaryAssetsSize":7950}},"assetsByChunkName":{"polyfill":["webpack-runtime-f7abd37263ef5f9b6cab.js","polyfill-5e40f9ff782d94fbed19.js"],"app":["webpack-runtime-f7abd37263ef5f9b6cab.js","framework-587f98a0a1a6eaf716e3.js","app-e33d6fbe3bb332ff4936.js"],"component---src-pages-404-tsx":["component---src-pages-404-tsx-616da19c675861e2db87.js"],"component---src-pages-index-tsx":["component---src-pages-index-tsx-233fda072165a386d4f8.js"]},"childAssetsByChunkName":{}}